funcguard/__init__.py
funcguard/calculate.py
funcguard/core.py
funcguard/ip_utils.py
funcguard/printer.py
funcguard/time_utils.py
funcguard/tools.py
funcguard/pd_utils/__init__.py
funcguard/pd_utils/convert_utils.py
funcguard/pd_utils/fill_round.py
funcguard/pd_utils/json_utils/__init__.py
funcguard/pd_utils/json_utils/json_parser.py
funcguard-0.2.10.dist-info/licenses/LICENSE
tests/__init__.py
funcguard-0.2.10.dist-info/METADATA
funcguard-0.2.10.dist-info/WHEEL
funcguard-0.2.10.dist-info/top_level.txt
funcguard-0.2.10.dist-info/RECORD
