Metadata-Version: 2.4
Name: funcguard
Version: 0.2.10
Summary: FuncGuard是一个Python库，提供函数执行超时控制、重试机制、HTTP请求封装和格式化打印工具。
Home-page: https://github.com/tinycen/funcguard
Author: tinycen
Author-email: sky_ruocen@qq.com
Classifier: Programming Language :: Python :: 3
Classifier: License :: OSI Approved :: MIT License
Classifier: Operating System :: OS Independent
Requires-Python: >=3.10
License-File: LICENSE
Requires-Dist: requests
Requires-Dist: pandas
Dynamic: author
Dynamic: author-email
Dynamic: classifier
Dynamic: description
Dynamic: description-content-type
Dynamic: home-page
Dynamic: license-file
Dynamic: requires-dist
Dynamic: requires-python
Dynamic: summary
